MANIFEST.in
py26-requirements.txt
requirements.txt
setup.cfg
setup.py
test-requirements.txt
asynx_core/__init__.py
asynx_core/_util.py
asynx_core/taskqueue.py
asynx_core/version.txt
asynx_core.egg-info/PKG-INFO
asynx_core.egg-info/SOURCES.txt
asynx_core.egg-info/dependency_links.txt
asynx_core.egg-info/requires.txt
asynx_core.egg-info/top_level.txt
asynx_core.egg-info/zip-safe
tests/test_taskqueue.py