Metadata-Version: 1.1
Name: asynx-core
Version: 0.4dev1
Summary: Core of the open source, distributed, and web / HTTP oriented taskqueue & scheduler service inspired by Google App Engine
Home-page: https://github.com/guokr/asynx
Author: Guokr
Author-email: bug@guokr.com
License: UNKNOWN
Platform: UNKNOWN
Classifier: Development Status :: 3 - Alpha
Classifier: Environment :: Web Environment
Classifier: Intended Audience :: Developers
Classifier: License :: OSI Approved :: MIT License
Classifier: Operating System :: OS Independent
Classifier: Programming Language :: Python
Classifier: Programming Language :: Python :: 2
Classifier: Programming Language :: Python :: 2.6
Classifier: Programming Language :: Python :: 2.7
Classifier: Programming Language :: Python :: 3
Classifier: Programming Language :: Python :: 3.3
Classifier: Topic :: Software Development :: Libraries :: Python Modules
